fortimanager_template_sync/__init__.py
fortimanager_template_sync/__main__.py
fortimanager_template_sync/common_task.py
fortimanager_template_sync/config.py
fortimanager_template_sync/deploy_run.py
fortimanager_template_sync/deploy_task.py
fortimanager_template_sync/exceptions.py
fortimanager_template_sync/misc.py
fortimanager_template_sync/sync_run.py
fortimanager_template_sync/sync_task.py
fortimanager_template_sync/fmg_api/__init__.py
fortimanager_template_sync/fmg_api/connection.py
fortimanager_template_sync/fmg_api/data.py
fortimanager_template_sync-0.0.1.post1.dist-info/entry_points.txt
fortimanager_template_sync-0.0.1.post1.dist-info/LICENSE.txt
fortimanager_template_sync-0.0.1.post1.dist-info/WHEEL
fortimanager_template_sync-0.0.1.post1.dist-info/METADATA
fortimanager_template_sync-0.0.1.post1.dist-info/RECORD
