Metadata-Version: 2.1
Name: fortimanager_template_sync
Version: 0.0.1.post1
Summary: FortiManager Template Sync
Author-email: Viktor Kertesz <vkertesz2@gmail.com>
Requires-Python: >=3.9,<4
Classifier: License :: OSI Approved :: MIT License
Classifier: Operating System :: Microsoft :: Windows
Classifier: Operating System :: POSIX :: Linux
Classifier: Programming Language :: Python :: 3
Classifier: Topic :: System :: Networking
Requires-Dist: GitPython
Requires-Dist: pydantic>2,<3
Requires-Dist: typer
Requires-Dist: pydantic-settings
Requires-Dist: more-itertools
Requires-Dist: pyfortinet
Requires-Dist: jinja2
Requires-Dist: ruamel.yaml
Requires-Dist: python-dotenv
Requires-Dist: pytest-cov ; extra == "dev"
Requires-Dist: pytest ; extra == "dev"
Requires-Dist: pytest-dependency ; extra == "dev"
Requires-Dist: flit ; extra == "dev"
Requires-Dist: invoke ; extra == "dev"
Requires-Dist: ruff ; extra == "dev"
Requires-Dist: pre-commit ; extra == "dev"
Requires-Dist: mypy ; extra == "dev"
Requires-Dist: mkdocs-material ; extra == "dev"
Requires-Dist: mkdocs-material-extensions ; extra == "dev"
Requires-Dist: mkdocs-gen-files ; extra == "dev"
Requires-Dist: mkdocstrings-python ; extra == "dev"
Requires-Dist: mkdocs-section-index ; extra == "dev"
Requires-Dist: mkdocs-literate-nav ; extra == "dev"
Requires-Dist: mkdocs-autorefs ; extra == "dev"
Requires-Dist: rich ; extra == "rich"
Project-URL: Documentation, https://realvitya.github.io/fortimanager-template-sync/
Project-URL: Source, https://github.com/realvitya/fortimanager-template-sync
Provides-Extra: dev
Provides-Extra: rich
